LICENSE
MANIFEST.in
README.md
setup.cfg
setup.py
django_drf_auth.egg-info/PKG-INFO
django_drf_auth.egg-info/SOURCES.txt
django_drf_auth.egg-info/dependency_links.txt
django_drf_auth.egg-info/not-zip-safe
django_drf_auth.egg-info/requires.txt
django_drf_auth.egg-info/top_level.txt
drf_auth/__init__.py
drf_auth/admin.py
drf_auth/apps.py
drf_auth/tasks.py
drf_auth/tests.py
drf_auth/urls.py
drf_auth/views.py
drf_auth/migrations/__init__.py
tests/__init__.py
tests/tests.py