Metadata-Version: 2.1
Name: django-drf-auth
Version: 0.1
Summary: REST API endpoints for Authentication and Registration
Home-page: https://github.com/thomas545/django-drf-auth/
Author: Thomas Adel
Author-email: thomas.adel31@gmail.com
License: MIT
Keywords: django drf auth rest-framework-authentication api
Platform: UNKNOWN
Classifier: Framework :: Django
Classifier: Intended Audience :: Developers
Classifier: Intended Audience :: System Administrators
Classifier: Operating System :: OS Independent
Classifier: Topic :: Software Development
